setup.py
ngbd_probability_distributions/Binomialdistribution.py
ngbd_probability_distributions/Gaussiandistribution.py
ngbd_probability_distributions/Generaldistribution.py
ngbd_probability_distributions/__init__.py
ngbd_probability_distributions.egg-info/PKG-INFO
ngbd_probability_distributions.egg-info/SOURCES.txt
ngbd_probability_distributions.egg-info/dependency_links.txt
ngbd_probability_distributions.egg-info/not-zip-safe
ngbd_probability_distributions.egg-info/top_level.txt