Metadata-Version: 1.0
Name: ngbd-probability-distributions
Version: 0.1
Summary: Normal, Gaussian, Binomial distributions
Home-page: UNKNOWN
Author: UNKNOWN
Author-email: UNKNOWN
License: UNKNOWN
Platform: UNKNOWN
